{"updateTime":"25.04.2023 / 18:37:14","sortData":[["TOWN/USDT",4.9,{"market":"MEXC","url":"https://www.mexc.com/exchange/TOWN_USDT","buyPrice":0.02834,"buyQty":721.56,"sellPrice":0.02771,"sellQty":267.53,"fee":[[280,"TOWN",600,"ERC20"]]},{"market":"OKX","url":"https://www.okx.com/ua/trade-spot/TOWN-USDT","buyPrice":0.0301,"buyQty":6.66,"sellPrice":0.02973,"sellQty":395.69,"fee":[]}],["UMEE/USDT",4.06,{"market":"MEXC","url":"https://www.mexc.com/exchange/UMEE_USDT","buyPrice":0.006852,"buyQty":1690,"sellPrice":0.006816,"sellQty":68,"fee":[[50,"UMEE",100,"ERC20"],[0.1,"UMEE",1,"OSMO"],[0.01,"UMEE",10,"UMEE"]]},{"market":"OKX","url":"https://www.okx.com/ua/trade-spot/UMEE-USDT","buyPrice":0.00714,"buyQty":10,"sellPrice":0.00713,"sellQty":208,"fee":[]}],["PRQ/USDT",3.13,{"market":"OKX","url":"https://www.okx.com/ua/trade-spot/PRQ-USDT","buyPrice":0.0987,"buyQty":1628.6,"sellPrice":0.0986,"sellQty":10.14,"fee":[]},{"market":"EXMO","url":"https://exmo.com/ru/trade/PRQ_USDT","buyPrice":0.1065,"buyQty":285.43,"sellPrice":0.10179093,"sellQty":972.58,"fee":[[20,"PRQ",100,"PRQ"]]}],["LOON/USDT",2.72,{"market":"MEXC","url":"https://www.mexc.com/exchange/LOON_USDT","buyPrice":0.005214,"buyQty":4031,"sellPrice":0.005155,"sellQty":1322,"fee":[[1228,"LOON",1000,"ERC20"]]},{"market":"OKX","url":"https://www.okx.com/ua/trade-spot/LOON-USDT","buyPrice":0.005372,"buyQty":10,"sellPrice":0.005356,"sellQty":133779,"fee":[]}],["WXT/USDT",2.6,{"market":"OKX","url":"https://www.okx.com/ua/trade-spot/WXT-USDT","buyPrice":0.00346,"buyQty":4985,"sellPrice":0.00345,"sellQty":76374,"fee":[]},{"market":"EXMO","url":"https://exmo.com/ru/trade/WXT_USDT","buyPrice":0.00357931,"buyQty":41866,"sellPrice":0.00355,"sellQty":100,"fee":[[50,"WXT",250,"WXT"],[200,"WXT",500,"WXT (ERC20)"]]}],["SXP/USDT",2.46,{"market":"MEXC","url":"https://www.mexc.com/exchange/SXP_USDT","buyPrice":0.5202,"buyQty":900,"sellPrice":0.5184,"sellQty":598.87,"fee":[[1,"SXP",2,"SXP"]]},{"market":"BINANCE","url":"https://www.binance.com/uk-UA/trade/SXP_USDT?theme=dark&type=spot","buyPrice":0.5332,"buyQty":672.9,"sellPrice":0.533,"sellQty":152.3,"fee":[[0.28,"SXP",0.56,"BNB Smart Chain (BEP20)"],[11,"SXP",22,"Ethereum (ERC20)"]]}],["MRST/USDT",1.73,{"market":"OKX","url":"https://www.okx.com/ua/trade-spot/MRST-USDT","buyPrice":0.00519,"buyQty":2381,"sellPrice":0.00518,"sellQty":235,"fee":[]},{"market":"MEXC","url":"https://www.mexc.com/exchange/MRST_USDT","buyPrice":0.00536,"buyQty":1506,"sellPrice":0.00528,"sellQty":11239,"fee":[[10,"MRST",20,"MATIC"]]}],["PIT/USDT",0.89,{"market":"OKX","url":"https://www.okx.com/ua/trade-spot/PIT-USDT","buyPrice":4.85e-10,"buyQty":1197685216942,"sellPrice":4.84e-10,"sellQty":9944058920,"fee":[]},{"market":"MEXC","url":"https://www.mexc.com/exchange/PIT_USDT","buyPrice":4.977e-10,"buyQty":505397420045,"sellPrice":4.893e-10,"sellQty":131029245258,"fee":[[1370760060,"PIT",20000000,"BEP20(BSC)"]]}],["BORING/USDT",0.75,{"market":"OKX","url":"https://www.okx.com/ua/trade-spot/BORING-USDT","buyPrice":0.00267,"buyQty":22938,"sellPrice":0.00266,"sellQty":202695,"fee":[]},{"market":"MEXC","url":"https://www.mexc.com/exchange/BORING_USDT","buyPrice":0.002741,"buyQty":11017,"sellPrice":0.00269,"sellQty":3970,"fee":[[1641,"BORING",300,"ERC20"],[42,"BORING",30,"BEP20(BSC)"]]}],["BABYDOGE/USDT",0.71,{"market":"OKX","url":"https://www.okx.com/ua/trade-spot/BABYDOGE-USDT","buyPrice":2.813e-9,"buyQty":129050801,"sellPrice":2.806e-9,"sellQty":4002497506,"fee":[]},{"market":"MEXC","url":"https://www.mexc.com/exchange/BABYDOGE_USDT","buyPrice":2.8331e-9,"buyQty":499753398666,"sellPrice":2.833e-9,"sellQty":503222243228,"fee":[[620919163,"BABYDOGE",800000000,"BEP20(BSC)"]]}],["SRM/USDT",0.69,{"market":"OKX","url":"https://www.okx.com/ua/trade-spot/SRM-USDT","buyPrice":0.145,"buyQty":3469.19,"sellPrice":0.144,"sellQty":12406.46,"fee":[]},{"market":"MEXC","url":"https://www.mexc.com/exchange/SRM_USDT","buyPrice":0.1468,"buyQty":590.59,"sellPrice":0.146,"sellQty":136.49,"fee":[[57,"SRM",6,"ERC20"],[3.8,"SRM",10,"SOL"]]}],["HIFI/USDT",0.6,{"market":"MEXC","url":"https://www.mexc.com/exchange/HIFI_USDT","buyPrice":0.4016,"buyQty":86.29,"sellPrice":0.399,"sellQty":477,"fee":[[1,"HIFI",2,"ETH"]]},{"market":"BINANCE","url":"https://www.binance.com/uk-UA/trade/HIFI_USDT?theme=dark&type=spot","buyPrice":0.4042,"buyQty":9126.1,"sellPrice":0.404,"sellQty":61.9,"fee":[[15,"HIFI",30,"Ethereum (ERC20)"]]}],["IQ/USDT",0.54,{"market":"MEXC","url":"https://www.mexc.com/exchange/IQ_USDT","buyPrice":0.005729,"buyQty":1649,"sellPrice":0.005709,"sellQty":1494,"fee":[[150,"IQ",750,"EOS"],[1099,"IQ",500,"ERC20"]]},{"market":"OKX","url":"https://www.okx.com/ua/trade-spot/IQ-USDT","buyPrice":0.0058,"buyQty":102,"sellPrice":0.00576,"sellQty":397,"fee":[]}],["MXT/USDT",0.49,{"market":"MEXC","url":"https://www.mexc.com/exchange/MXT_USDT","buyPrice":0.0020032,"buyQty":18011,"sellPrice":0.002,"sellQty":3825,"fee":[[4173,"MXT",4000,"ERC20"]]},{"market":"OKX","url":"https://www.okx.com/ua/trade-spot/MXT-USDT","buyPrice":0.002014,"buyQty":249800,"sellPrice":0.002013,"sellQty":1695896,"fee":[]}],["BOND/USDT",0.36,{"market":"MEXC","url":"https://www.mexc.com/exchange/BOND_USDT","buyPrice":4.428,"buyQty":1.39,"sellPrice":4.311,"sellQty":15.54,"fee":[[2.9,"BOND",1,"ERC20"]]},{"market":"BINANCE","url":"https://www.binance.com/uk-UA/trade/BOND_USDT?theme=dark&type=spot","buyPrice":4.447,"buyQty":102.23,"sellPrice":4.444,"sellQty":20,"fee":[[0.4,"BOND",0.8,"Ethereum (ERC20)"]]}],["NBT/USDT",0.35,{"market":"MEXC","url":"https://www.mexc.com/exchange/NBT_USDT","buyPrice":0.00284,"buyQty":28517,"sellPrice":0.002839,"sellQty":12303,"fee":[[150,"NBT",300,"BEP20(BSC)"],[900,"NBT",2000,"ERC20"]]},{"market":"BINANCE","url":"https://www.binance.com/uk-UA/trade/NBT_USDT?theme=dark&type=spot","buyPrice":0.00288,"buyQty":24757,"sellPrice":0.00285,"sellQty":578653,"fee":[]}],["RIO/USDT",0.33,{"market":"MEXC","url":"https://www.mexc.com/exchange/RIO_USDT","buyPrice":0.2133,"buyQty":93.54,"sellPrice":0.2126,"sellQty":358.58,"fee":[[3,"RIO",10,"ALGO"]]},{"market":"OKX","url":"https://www.okx.com/ua/trade-spot/RIO-USDT","buyPrice":0.2146,"buyQty":7.98,"sellPrice":0.214,"sellQty":1.01,"fee":[]}],["THG/USDT",0.33,{"market":"OKX","url":"https://www.okx.com/ua/trade-spot/THG-USDT","buyPrice":0.067,"buyQty":2.92,"sellPrice":0.0669,"sellQty":157.52,"fee":[]},{"market":"MEXC","url":"https://www.mexc.com/exchange/THG_USDT","buyPrice":0.06723,"buyQty":98.16,"sellPrice":0.06722,"sellQty":64.17,"fee":[[4,"THG",0.4,"BEP20(BSC)"]]}],["KSM/USDT",0.29,{"market":"MEXC","url":"https://www.mexc.com/exchange/KSM_USDT","buyPrice":29.5943,"buyQty":7.795,"sellPrice":29.5631,"sellQty":14.313,"fee":[[0.01,"KSM",0.02,"KSM"]]},{"market":"BINANCE","url":"https://www.binance.com/uk-UA/trade/KSM_USDT?theme=dark&type=spot","buyPrice":29.7,"buyQty":109.467,"sellPrice":29.68,"sellQty":2.712,"fee":[[0.0023,"KSM",0.0046,"BNB Smart Chain (BEP20)"],[0.01,"KSM",1.01,"Kusama"]]}],["TON/USDT",0.22,{"market":"MEXC","url":"https://www.mexc.com/exchange/TON_USDT","buyPrice":2.25,"buyQty":885.53,"sellPrice":2.249,"sellQty":915.18,"fee":[[0.02,"TON",1,"TONCOIN"],[0.47,"TON",1,"BEP20(BSC)"],[3,"TON",6,"ERC20"]]},{"market":"EXMO","url":"https://exmo.com/ru/trade/TON_USDT","buyPrice":2.289999,"buyQty":38.33,"sellPrice":2.255,"sellQty":119.68,"fee":[[0.1,"TON",15,"TON"]]}],["CONV/USDT",0.21,{"market":"OKX","url":"https://www.okx.com/ua/trade-spot/CONV-USDT","buyPrice":0.000567,"buyQty":6014,"sellPrice":0.000565,"sellQty":52560,"fee":[]},{"market":"MEXC","url":"https://www.mexc.com/exchange/CONV_USDT","buyPrice":0.0005693,"buyQty":11272,"sellPrice":0.0005682,"sellQty":153451,"fee":[[7982,"CONV",40000,"ERC20"]]}],["UTK/USDT",0.18,{"market":"BINANCE","url":"https://www.binance.com/uk-UA/trade/UTK_USDT?theme=dark&type=spot","buyPrice":0.1097,"buyQty":12870,"sellPrice":0.1096,"sellQty":6742,"fee":[[64,"UTK",128,"Ethereum (ERC20)"],[1,"UTK",20,"MultiversX eGold"]]},{"market":"OKX","url":"https://www.okx.com/ua/trade-spot/UTK-USDT","buyPrice":0.11,"buyQty":2618.4,"sellPrice":0.1099,"sellQty":8,"fee":[]}],["WNCG/USDT",0.14,{"market":"MEXC","url":"https://www.mexc.com/exchange/WNCG_USDT","buyPrice":0.08718,"buyQty":579,"sellPrice":0.08692,"sellQty":585.65,"fee":[[89,"WNCG",30,"ERC20"]]},{"market":"OKX","url":"https://www.okx.com/ua/trade-spot/WNCG-USDT","buyPrice":0.0875,"buyQty":933.93,"sellPrice":0.0873,"sellQty":3615.31,"fee":[]}],["RVN/USDT",0.13,{"market":"OKX","url":"https://www.okx.com/ua/trade-spot/RVN-USDT","buyPrice":0.02383,"buyQty":15200,"sellPrice":0.02382,"sellQty":19595.4,"fee":[]},{"market":"BINANCE","url":"https://www.binance.com/uk-UA/trade/RVN_USDT?theme=dark&type=spot","buyPrice":0.02387,"buyQty":23971.9,"sellPrice":0.02386,"sellQty":16509.2,"fee":[[1,"RVN",2,"Ravencoin"]]}],["LUNC/USDT",0.13,{"market":"OKX","url":"https://www.okx.com/ua/trade-spot/LUNC-USDT","buyPrice":0.00010841,"buyQty":1318152,"sellPrice":0.0001084,"sellQty":1620970,"fee":[]},{"market":"MEXC","url":"https://www.mexc.com/exchange/LUNC_USDT","buyPrice":0.00010857,"buyQty":12771706,"sellPrice":0.00010855,"sellQty":10851939,"fee":[[100,"LUNC",1000,"LUNC"]]}],["MIR/USDT",0.13,{"market":"OKX","url":"https://www.okx.com/ua/trade-spot/MIR-USDT","buyPrice":0.077,"buyQty":15523.27,"sellPrice":0.076,"sellQty":317.49,"fee":[]},{"market":"MEXC","url":"https://www.mexc.com/exchange/MIR_USDT","buyPrice":0.0777,"buyQty":1163.7,"sellPrice":0.0771,"sellQty":294.29,"fee":[[126,"MIR",50,"ERC20"]]}],["BTT/USDT",0.11,{"market":"MEXC","url":"https://www.mexc.com/exchange/BTT_USDT","buyPrice":6.273e-7,"buyQty":29503236,"sellPrice":6.265e-7,"sellQty":1758418309,"fee":[[500000,"BTT",520000,"TRC20"],[521285,"BTT",400000,"BEP20(BSC)"]]},{"market":"OKX","url":"https://www.okx.com/ua/trade-spot/BTT-USDT","buyPrice":6.29e-7,"buyQty":220619273,"sellPrice":6.28e-7,"sellQty":1380412547,"fee":[]}],["IOST/USDT",0.1,{"market":"OKX","url":"https://www.okx.com/ua/trade-spot/IOST-USDT","buyPrice":0.01013,"buyQty":66896.86,"sellPrice":0.01012,"sellQty":119251.84,"fee":[]},{"market":"BINANCE","url":"https://www.binance.com/uk-UA/trade/IOST_USDT?theme=dark&type=spot","buyPrice":0.01015,"buyQty":1011378,"sellPrice":0.01014,"sellQty":6632,"fee":[[1,"IOST",2,"IOST"],[634,"IOST",1268,"Ethereum (ERC20)"]]}],["XTZ/USDT",0.1,{"market":"OKX","url":"https://www.okx.com/ua/trade-spot/XTZ-USDT","buyPrice":0.979,"buyQty":355,"sellPrice":0.978,"sellQty":967.57,"fee":[]},{"market":"BINANCE","url":"https://www.binance.com/uk-UA/trade/XTZ_USDT?theme=dark&type=spot","buyPrice":0.981,"buyQty":14590.4,"sellPrice":0.98,"sellQty":2607.7,"fee":[[0.02,"XTZ",0.1,"BNB Smart Chain (BEP20)"],[0.1,"XTZ",1,"Tezos"],[0.17,"XTZ",0.34,"BNB Beacon Chain (BEP2)"]]}],["PERP/USDT",0.1,{"market":"OKX","url":"https://www.okx.com/ua/trade-spot/PERP-USDT","buyPrice":0.692,"buyQty":712.67,"sellPrice":0.691,"sellQty":6375.45,"fee":[]},{"market":"BINANCE","url":"https://www.binance.com/uk-UA/trade/PERP_USDT?theme=dark&type=spot","buyPrice":0.69301,"buyQty":216.2,"sellPrice":0.69269,"sellQty":55,"fee":[[0.095,"PERP",0.19,"BNB Smart Chain (BEP20)"],[9.2,"PERP",18,"Ethereum (ERC20)"]]}],["GARI/USDT",0.1,{"market":"OKX","url":"https://www.okx.com/ua/trade-spot/GARI-USDT","buyPrice":0.0499,"buyQty":106.22,"sellPrice":0.0497,"sellQty":103.21,"fee":[]},{"market":"MEXC","url":"https://www.mexc.com/exchange/GARI_USDT","buyPrice":0.04996,"buyQty":125.91,"sellPrice":0.04995,"sellQty":5668.03,"fee":[[47,"GARI",50,"SOL"]]}],["MULTI/USDT",0.09,{"market":"MEXC","url":"https://www.mexc.com/exchange/MULTI_USDT","buyPrice":9.302,"buyQty":2.37,"sellPrice":9.178,"sellQty":2.28,"fee":[[0.06,"MULTI",0.1,"BEP20(BSC)"],[0.25,"MULTI",1,"ERC20"]]},{"market":"BINANCE","url":"https://www.binance.com/uk-UA/trade/MULTI_USDT?theme=dark&type=spot","buyPrice":9.32,"buyQty":1.27,"sellPrice":9.31,"sellQty":107.48,"fee":[[0.0086,"MULTI",0.017,"BNB Smart Chain (BEP20)"]]}],["RON/USDT",0.09,{"market":"OKX","url":"https://www.okx.com/ua/trade-spot/RON-USDT","buyPrice":1.059,"buyQty":280.91,"sellPrice":1.058,"sellQty":118.9,"fee":[]},{"market":"MEXC","url":"https://www.mexc.com/exchange/RON_USDT","buyPrice":1.0608,"buyQty":275.29,"sellPrice":1.06,"sellQty":4.72,"fee":[[0.1,"RON",1,"RONIN"]]}],["ZEN/USDT",0.08,{"market":"MEXC","url":"https://www.mexc.com/exchange/ZEN_USDT","buyPrice":9.432,"buyQty":20.96,"sellPrice":9.423,"sellQty":1.2,"fee":[[0.01,"ZEN",0.2,"ZEN"]]},{"market":"OKX","url":"https://www.okx.com/ua/trade-spot/ZEN-USDT","buyPrice":9.45,"buyQty":194.66,"sellPrice":9.44,"sellQty":0,"fee":[]}],["BICO/USDT",0.08,{"market":"MEXC","url":"https://www.mexc.com/exchange/BICO_USDT","buyPrice":0.3627,"buyQty":62.9,"sellPrice":0.3601,"sellQty":76.42,"fee":[[15,"BICO",5,"ERC20"]]},{"market":"OKX","url":"https://www.okx.com/ua/trade-spot/BICO-USDT","buyPrice":0.364,"buyQty":3871.08,"sellPrice":0.363,"sellQty":1500,"fee":[]}],["XRP/USDT",0.07,{"market":"OKX","url":"https://www.okx.com/ua/trade-spot/XRP-USDT","buyPrice":0.45626,"buyQty":901.11,"sellPrice":0.45625,"sellQty":945.52,"fee":[]},{"market":"BINANCE","url":"https://www.binance.com/uk-UA/trade/XRP_USDT?theme=dark&type=spot","buyPrice":0.4567,"buyQty":210316,"sellPrice":0.4566,"sellQty":704,"fee":[[0.24,"XRP",0.48,"BNB Smart Chain (BEP20)"],[0.2,"XRP",30,"Ripple"],[0.36,"XRP",0.72,"BNB Beacon Chain (BEP2)"],[14,"XRP",28,"Ethereum (ERC20)"]]}],["PHA/USDT",0.07,{"market":"BINANCE","url":"https://www.binance.com/uk-UA/trade/PHA_USDT?theme=dark&type=spot","buyPrice":0.1362,"buyQty":1007,"sellPrice":0.1361,"sellQty":1638,"fee":[[0.54,"PHA",1.08,"BNB Smart Chain (BEP20)"],[16,"PHA",32,"Ethereum (ERC20)"]]},{"market":"OKX","url":"https://www.okx.com/ua/trade-spot/PHA-USDT","buyPrice":0.1365,"buyQty":3500,"sellPrice":0.1363,"sellQty":1797.83,"fee":[]}],["HFT/USDT",0.07,{"market":"MEXC","url":"https://www.mexc.com/exchange/HFT_USDT","buyPrice":0.5465,"buyQty":1746.69,"sellPrice":0.5464,"sellQty":1577.71,"fee":[[17,"HFT",20,"ERC20"],[0.25,"HFT",1,"BEP20(BSC)"]]},{"market":"BINANCE","url":"https://www.binance.com/uk-UA/trade/HFT_USDT?theme=dark&type=spot","buyPrice":0.547,"buyQty":935.7,"sellPrice":0.5469,"sellQty":126.3,"fee":[[0.13,"HFT",0.26,"BNB Smart Chain (BEP20)"],[11,"HFT",22,"Ethereum (ERC20)"]]}],["EOS/USDT",0.06,{"market":"OKX","url":"https://www.okx.com/ua/trade-spot/EOS-USDT","buyPrice":1.0284,"buyQty":395.39,"sellPrice":1.0282,"sellQty":29.18,"fee":[]},{"market":"BINANCE","url":"https://www.binance.com/uk-UA/trade/EOS_USDT?theme=dark&type=spot","buyPrice":1.03,"buyQty":41261.6,"sellPrice":1.029,"sellQty":19962.8,"fee":[[0.081,"EOS",0.16,"BNB Smart Chain (BEP20)"],[0.08,"EOS",0.2,"EOS"],[0.16,"EOS",0.32,"BNB Beacon Chain (BEP2)"]]}],["ATOM/USDT",0.06,{"market":"OKX","url":"https://www.okx.com/ua/trade-spot/ATOM-USDT","buyPrice":10.76,"buyQty":23,"sellPrice":10.757,"sellQty":36.716,"fee":[]},{"market":"BINANCE","url":"https://www.binance.com/uk-UA/trade/ATOM_USDT?theme=dark&type=spot","buyPrice":10.767,"buyQty":193.37,"sellPrice":10.766,"sellQty":589.34,"fee":[[0.0072,"ATOM",0.014,"BNB Smart Chain (BEP20)"],[0.004,"ATOM",0.01,"Cosmos"],[0.015,"ATOM",0.03,"BNB Beacon Chain (BEP2)"]]}],["LRC/USDT",0.06,{"market":"OKX","url":"https://www.okx.com/ua/trade-spot/LRC-USDT","buyPrice":0.3315,"buyQty":1500,"sellPrice":0.3314,"sellQty":1500,"fee":[]},{"market":"BINANCE","url":"https://www.binance.com/uk-UA/trade/LRC_USDT?theme=dark&type=spot","buyPrice":0.3318,"buyQty":20368,"sellPrice":0.3317,"sellQty":569,"fee":[[0.25,"LRC",0.5,"BNB Smart Chain (BEP20)"],[19,"LRC",38,"Ethereum (ERC20)"]]}],["STORJ/USDT",0.06,{"market":"OKX","url":"https://www.okx.com/ua/trade-spot/STORJ-USDT","buyPrice":0.3439,"buyQty":130.52,"sellPrice":0.3437,"sellQty":700,"fee":[]},{"market":"BINANCE","url":"https://www.binance.com/uk-UA/trade/STORJ_USDT?theme=dark&type=spot","buyPrice":0.3444,"buyQty":2546,"sellPrice":0.3441,"sellQty":539,"fee":[[18,"STORJ",36,"Ethereum (ERC20)"]]}],["MASK/USDT",0.06,{"market":"OKX","url":"https://www.okx.com/ua/trade-spot/MASK-USDT","buyPrice":4.816,"buyQty":296.26,"sellPrice":4.815,"sellQty":51.87,"fee":[]},{"market":"BINANCE","url":"https://www.binance.com/uk-UA/trade/MASK_USDT?theme=dark&type=spot","buyPrice":4.82,"buyQty":352,"sellPrice":4.819,"sellQty":376.4,"fee":[[0.024,"MASK",0.048,"BNB Smart Chain (BEP20)"],[1.41,"MASK",2.82,"Ethereum (ERC20)"]]}],["GLMR/USDT",0.06,{"market":"OKX","url":"https://www.okx.com/ua/trade-spot/GLMR-USDT","buyPrice":0.348,"buyQty":1400,"sellPrice":0.3476,"sellQty":590.3,"fee":[]},{"market":"BINANCE","url":"https://www.binance.com/uk-UA/trade/GLMR_USDT?theme=dark&type=spot","buyPrice":0.3484,"buyQty":3671.1,"sellPrice":0.3482,"sellQty":375.3,"fee":[[0.01,"GLMR",1,"Moonbeam"],[0.21,"GLMR",0.42,"BNB Smart Chain (BEP20)"]]}],["APE/USDT",0.06,{"market":"OKX","url":"https://www.okx.com/ua/trade-spot/APE-USDT","buyPrice":3.8545,"buyQty":130,"sellPrice":3.854,"sellQty":77.84,"fee":[]},{"market":"BINANCE","url":"https://www.binance.com/uk-UA/trade/APE_USDT?theme=dark&type=spot","buyPrice":3.858,"buyQty":455.53,"sellPrice":3.857,"sellQty":4.52,"fee":[[0.018,"APE",0.036,"BNB Smart Chain (BEP20)"],[1.64,"APE",3.28,"Ethereum (ERC20)"]]}],["APT/USDT",0.06,{"market":"OKX","url":"https://www.okx.com/ua/trade-spot/APT-USDT","buyPrice":9.853,"buyQty":57.19,"sellPrice":9.8513,"sellQty":45,"fee":[]},{"market":"BINANCE","url":"https://www.binance.com/uk-UA/trade/APT_USDT?theme=dark&type=spot","buyPrice":9.859,"buyQty":144.99,"sellPrice":9.8586,"sellQty":2.38,"fee":[[0.01,"APT",0.02,"APT"]]}],["BONE/USDT",0.06,{"market":"MEXC","url":"https://www.mexc.com/exchange/BONE_USDT","buyPrice":1.0327,"buyQty":2669.97,"sellPrice":1.0293,"sellQty":6.57,"fee":[[7.55,"BONE",10,"ERC20"]]},{"market":"OKX","url":"https://www.okx.com/ua/trade-spot/BONE-USDT","buyPrice":1.034,"buyQty":94.29,"sellPrice":1.0333,"sellQty":1.02,"fee":[]}],["ETH/USDT",0.05,{"market":"OKX","url":"https://www.okx.com/ua/trade-spot/ETH-USDT","buyPrice":1814.05,"buyQty":13.37058,"sellPrice":1814.04,"sellQty":0.02857,"fee":[]},{"market":"BINANCE","url":"https://www.binance.com/uk-UA/trade/ETH_USDT?theme=dark&type=spot","buyPrice":1814.9,"buyQty":83.5364,"sellPrice":1814.89,"sellQty":0.7309,"fee":[[0.000056,"ETH",0.00011,"BNB Smart Chain (BEP20)"],[0.00182,"ETH",0.0098,"Ethereum (ERC20)"],[0.00035,"ETH",0.0008,"Arbitrum One"],[0.00009,"ETH",0.00018,"BNB Beacon Chain (BEP2)"],[0.00035,"ETH",0.001,"Optimism"]]}],["NEAR/USDT",0.05,{"market":"OKX","url":"https://www.okx.com/ua/trade-spot/NEAR-USDT","buyPrice":1.863,"buyQty":948.83,"sellPrice":1.862,"sellQty":2382.25,"fee":[]},{"market":"BINANCE","url":"https://www.binance.com/uk-UA/trade/NEAR_USDT?theme=dark&type=spot","buyPrice":1.865,"buyQty":10876.7,"sellPrice":1.864,"sellQty":123.9,"fee":[[0.039,"NEAR",0.078,"BNB Smart Chain (BEP20)"],[0.01,"NEAR",0.2,"NEAR Protocol"],[0.089,"NEAR",0.18,"BNB Beacon Chain (BEP2)"]]}],["SOL/USDT",0.05,{"market":"OKX","url":"https://www.okx.com/ua/trade-spot/SOL-USDT","buyPrice":20.89,"buyQty":60.239,"sellPrice":20.889,"sellQty":0.046,"fee":[]},{"market":"BINANCE","url":"https://www.binance.com/uk-UA/trade/SOL_USDT?theme=dark&type=spot","buyPrice":20.91,"buyQty":2671.39,"sellPrice":20.9,"sellQty":1181.68,"fee":[[0.004,"SOL",0.008,"BNB Smart Chain (BEP20)"],[0.008,"SOL",0.02,"Solana"]]}],["LTC/USDT",0.05,{"market":"OKX","url":"https://www.okx.com/ua/trade-spot/LTC-USDT","buyPrice":88.84,"buyQty":42.634,"sellPrice":88.83,"sellQty":5.468,"fee":[]},{"market":"BINANCE","url":"https://www.binance.com/uk-UA/trade/LTC_USDT?theme=dark&type=spot","buyPrice":88.89,"buyQty":79.822,"sellPrice":88.88,"sellQty":2.169,"fee":[[0.00097,"LTC",0.0019,"BNB Smart Chain (BEP20)"],[0.001,"LTC",0.002,"Litecoin"],[0.0019,"LTC",0.0038,"BNB Beacon Chain (BEP2)"]]}],["QTUM/USDT",0.05,{"market":"OKX","url":"https://www.okx.com/ua/trade-spot/QTUM-USDT","buyPrice":2.796,"buyQty":85,"sellPrice":2.795,"sellQty":170,"fee":[]},{"market":"MEXC","url":"https://www.mexc.com/exchange/QTUM_USDT","buyPrice":2.8003,"buyQty":167.87,"sellPrice":2.7974,"sellQty":18.82,"fee":[[0.1,"QTUM",0.5,"QTUM"]]}],["CHZ/USDT",0.05,{"market":"OKX","url":"https://www.okx.com/ua/trade-spot/CHZ-USDT","buyPrice":0.12554,"buyQty":1888.53,"sellPrice":0.12552,"sellQty":4868,"fee":[]},{"market":"BINANCE","url":"https://www.binance.com/uk-UA/trade/CHZ_USDT?theme=dark&type=spot","buyPrice":0.1257,"buyQty":193320,"sellPrice":0.1256,"sellQty":68407,"fee":[[1.34,"CHZ",2.68,"BNB Beacon Chain (BEP2)"],[52,"CHZ",104,"Ethereum (ERC20)"]]}],["EGLD/USDT",0.05,{"market":"OKX","url":"https://www.okx.com/ua/trade-spot/EGLD-USDT","buyPrice":37.42,"buyQty":5.151,"sellPrice":37.41,"sellQty":0.272,"fee":[]},{"market":"BINANCE","url":"https://www.binance.com/uk-UA/trade/EGLD_USDT?theme=dark&type=spot","buyPrice":37.45,"buyQty":29.3,"sellPrice":37.44,"sellQty":5.34,"fee":[[0.0019,"EGLD",0.0038,"BNB Smart Chain (BEP20)"],[0.0008,"EGLD",0.01,"MultiversX eGold"]]}],["UMA/USDT",0.05,{"market":"OKX","url":"https://www.okx.com/ua/trade-spot/UMA-USDT","buyPrice":1.842,"buyQty":260,"sellPrice":1.841,"sellQty":197.81,"fee":[]},{"market":"BINANCE","url":"https://www.binance.com/uk-UA/trade/UMA_USDT?theme=dark&type=spot","buyPrice":1.847,"buyQty":419.8,"sellPrice":1.843,"sellQty":324.2,"fee":[[3.45,"UMA",6.9,"Ethereum (ERC20)"]]}],["QUICK/USDT",0.05,{"market":"MEXC","url":"https://www.mexc.com/exchange/QUICK_USDT","buyPrice":68.868,"buyQty":0.226,"sellPrice":68.369,"sellQty":0.169,"fee":[[0.00025,"QUICK",0.01,"MATIC"],[0.08,"QUICK",0.16,"ERC20"]]},{"market":"BINANCE","url":"https://www.binance.com/uk-UA/trade/QUICK_USDT?theme=dark&type=spot","buyPrice":69,"buyQty":14.785,"sellPrice":68.9,"sellQty":6.383,"fee":[[0.09,"QUICK",0.18,"Ethereum (ERC20)"],[0.0028,"QUICK",0.0056,"Polygon"]]}],["VGX/USDT",0.05,{"market":"MEXC","url":"https://www.mexc.com/exchange/VGX_USDT","buyPrice":0.3775,"buyQty":370.19,"sellPrice":0.377,"sellQty":302.04,"fee":[[27,"VGX",10,"ERC20"]]},{"market":"BINANCE","url":"https://www.binance.com/uk-UA/trade/VGX_USDT?theme=dark&type=spot","buyPrice":0.378,"buyQty":686.9,"sellPrice":0.3777,"sellQty":277.6,"fee":[[18,"VGX",36,"Ethereum (ERC20)"]]}],["LDO/USDT",0.05,{"market":"OKX","url":"https://www.okx.com/ua/trade-spot/LDO-USDT","buyPrice":2.028,"buyQty":168.27,"sellPrice":2.0279,"sellQty":2.06,"fee":[]},{"market":"BINANCE","url":"https://www.binance.com/uk-UA/trade/LDO_USDT?theme=dark&type=spot","buyPrice":2.03,"buyQty":9256.28,"sellPrice":2.029,"sellQty":309.11,"fee":[[3.12,"LDO",6.24,"Ethereum (ERC20)"]]}],["BTC/USDT",0.04,{"market":"OKX","url":"https://www.okx.com/ua/trade-spot/BTC-USDT","buyPrice":27335.8,"buyQty":3.405015,"sellPrice":27335.7,"sellQty":0.005333,"fee":[]},{"market":"BINANCE","url":"https://www.binance.com/uk-UA/trade/BTC_USDT?theme=dark&type=spot","buyPrice":27347.28,"buyQty":6.06381,"sellPrice":27347.27,"sellQty":0.00038,"fee":[[0.0000039,"BTC",0.0000078,"BNB Smart Chain (BEP20)"],[0.0002,"BTC",0.0003,"Bitcoin"],[0.000006,"BTC",0.000012,"BNB Beacon Chain (BEP2)"],[0.0005,"BTC",0.001,"BTC(SegWit)"],[0.00023,"BTC",0.00046,"Ethereum (ERC20)"]]}],["DOGE/USDT",0.04,{"market":"MEXC","url":"https://www.mexc.com/exchange/DOGE_USDT","buyPrice":0.07799,"buyQty":200554,"sellPrice":0.07798,"sellQty":188903.13,"fee":[[5,"DOGE",10,"DOGE"],[7,"DOGE",4,"BEP20(BSC)"]]},{"market":"BINANCE","url":"https://www.binance.com/uk-UA/trade/DOGE_USDT?theme=dark&type=spot","buyPrice":0.07803,"buyQty":146591,"sellPrice":0.07802,"sellQty":7620,"fee":[[1.1,"DOGE",2.2,"BNB Smart Chain (BEP20)"],[4,"DOGE",80,"dogecoin"],[2.11,"DOGE",4.22,"BNB Beacon Chain (BEP2)"]]}],["ONT/USDT",0.04,{"market":"OKX","url":"https://www.okx.com/ua/trade-spot/ONT-USDT","buyPrice":0.2311,"buyQty":1100,"sellPrice":0.231,"sellQty":1859.38,"fee":[]},{"market":"BINANCE","url":"https://www.binance.com/uk-UA/trade/ONT_USDT?theme=dark&type=spot","buyPrice":0.2314,"buyQty":6384,"sellPrice":0.2312,"sellQty":1242,"fee":[[0.35,"ONT",0.7,"BNB Smart Chain (BEP20)"],[1,"ONT",2,"Ontology"],[0.7,"ONT",1.4,"BNB Beacon Chain (BEP2)"]]}],["BAT/USDT",0.04,{"market":"OKX","url":"https://www.okx.com/ua/trade-spot/BAT-USDT","buyPrice":0.2417,"buyQty":1000,"sellPrice":0.2416,"sellQty":3763.26,"fee":[]},{"market":"BINANCE","url":"https://www.binance.com/uk-UA/trade/BAT_USDT?theme=dark&type=spot","buyPrice":0.2419,"buyQty":29555,"sellPrice":0.2418,"sellQty":260,"fee":[[0.3,"BAT",0.6,"BNB Smart Chain (BEP20)"],[0.67,"BAT",1.34,"BNB Beacon Chain (BEP2)"],[26,"BAT",52,"Ethereum (ERC20)"]]}],["CELR/USDT",0.04,{"market":"OKX","url":"https://www.okx.com/ua/trade-spot/CELR-USDT","buyPrice":0.02297,"buyQty":9500,"sellPrice":0.02296,"sellQty":30832.59,"fee":[]},{"market":"BINANCE","url":"https://www.binance.com/uk-UA/trade/CELR_USDT?theme=dark&type=spot","buyPrice":0.02299,"buyQty":4962.4,"sellPrice":0.02298,"sellQty":62536.2,"fee":[[4.38,"CELR",8.76,"BNB Smart Chain (BEP20)"],[289,"CELR",578,"Ethereum (ERC20)"]]}],["STX/USDT",0.04,{"market":"OKX","url":"https://www.okx.com/ua/trade-spot/STX-USDT","buyPrice":0.7167,"buyQty":1889.84,"sellPrice":0.7166,"sellQty":3.38,"fee":[]},{"market":"BINANCE","url":"https://www.binance.com/uk-UA/trade/STX_USDT?theme=dark&type=spot","buyPrice":0.7171,"buyQty":638.4,"sellPrice":0.717,"sellQty":280.8,"fee":[[1.5,"STX",5,"Stacks"]]}],["SAND/USDT",0.04,{"market":"OKX","url":"https://www.okx.com/ua/trade-spot/SAND-USDT","buyPrice":0.5701,"buyQty":987.01,"sellPrice":0.57,"sellQty":245.45,"fee":[]},{"market":"BINANCE","url":"https://www.binance.com/uk-UA/trade/SAND_USDT?theme=dark&type=spot","buyPrice":0.5704,"buyQty":7171,"sellPrice":0.5703,"sellQty":1279,"fee":[[0.13,"SAND",0.26,"BNB Smart Chain (BEP20)"],[11,"SAND",22,"Ethereum (ERC20)"],[0.34,"SAND",0.68,"Polygon"]]}],["FIL/USDT",0.04,{"market":"MEXC","url":"https://www.mexc.com/exchange/FIL_USDT","buyPrice":5.188,"buyQty":799.48,"sellPrice":5.187,"sellQty":3426.95,"fee":[[0.05,"FIL",0.12,"FIL"]]},{"market":"OKX","url":"https://www.okx.com/ua/trade-spot/FIL-USDT","buyPrice":5.191,"buyQty":2263.51,"sellPrice":5.19,"sellQty":0.08,"fee":[]}],["SLP/USDT",0.04,{"market":"BINANCE","url":"https://www.binance.com/uk-UA/trade/SLP_USDT?theme=dark&type=spot","buyPrice":0.002549,"buyQty":80649,"sellPrice":0.002548,"sellQty":10200,"fee":[[27,"SLP",54,"BNB Smart Chain (BEP20)"],[2502,"SLP",5004,"Ethereum (ERC20)"],[1,"SLP",154,"Ronin"]]},{"market":"OKX","url":"https://www.okx.com/ua/trade-spot/SLP-USDT","buyPrice":0.00256,"buyQty":3900191,"sellPrice":0.00255,"sellQty":365264,"fee":[]}],["DYDX/USDT",0.04,{"market":"OKX","url":"https://www.okx.com/ua/trade-spot/DYDX-USDT","buyPrice":2.409,"buyQty":736.42,"sellPrice":2.408,"sellQty":1400.55,"fee":[]},{"market":"BINANCE","url":"https://www.binance.com/uk-UA/trade/DYDX_USDT?theme=dark&type=spot","buyPrice":2.411,"buyQty":6076.03,"sellPrice":2.41,"sellQty":606.38,"fee":[[2.63,"DYDX",5.26,"Ethereum (ERC20)"]]}],["SANTOS/USDT",0.04,{"market":"BINANCE","url":"https://www.binance.com/uk-UA/trade/SANTOS_USDT?theme=dark&type=spot","buyPrice":4.792,"buyQty":54.53,"sellPrice":4.788,"sellQty":36.77,"fee":[[0.017,"SANTOS",0.034,"BNB Smart Chain (BEP20)"]]},{"market":"MEXC","url":"https://www.mexc.com/exchange/SANTOS_USDT","buyPrice":4.796,"buyQty":38.11,"sellPrice":4.794,"sellQty":10.06,"fee":[[0.1,"SANTOS",1,"BEP20(BSC)"]]}],["MAGIC/USDT",0.04,{"market":"OKX","url":"https://www.okx.com/ua/trade-spot/MAGIC-USDT","buyPrice":1.111,"buyQty":658.36,"sellPrice":1.11,"sellQty":5328.86,"fee":[]},{"market":"BINANCE","url":"https://www.binance.com/uk-UA/trade/MAGIC_USDT?theme=dark&type=spot","buyPrice":1.1116,"buyQty":53.3,"sellPrice":1.1114,"sellQty":61,"fee":[[0.3,"MAGIC",2,"Arbitrum One"]]}],["SSV/USDT",0.04,{"market":"OKX","url":"https://www.okx.com/ua/trade-spot/SSV-USDT","buyPrice":27.52,"buyQty":19,"sellPrice":27.49,"sellQty":26.292,"fee":[]},{"market":"BINANCE","url":"https://www.binance.com/uk-UA/trade/SSV_USDT?theme=dark&type=spot","buyPrice":27.54,"buyQty":21.425,"sellPrice":27.53,"sellQty":6.8,"fee":[[0.24,"SSV",0.48,"Ethereum (ERC20)"]]}],["ADA/USDT",0.03,{"market":"OKX","url":"https://www.okx.com/ua/trade-spot/ADA-USDT","buyPrice":0.37937,"buyQty":3797.3,"sellPrice":0.37936,"sellQty":1.03,"fee":[]},{"market":"MEXC","url":"https://www.mexc.com/exchange/ADA_USDT","buyPrice":0.3795,"buyQty":54615.8,"sellPrice":0.3795,"sellQty":58953.8,"fee":[[1,"ADA",10,"ADA"]]}],["DOT/USDT",0.03,{"market":"MEXC","url":"https://www.mexc.com/exchange/DOT_USDT","buyPrice":5.808,"buyQty":3130.96,"sellPrice":5.806,"sellQty":1655.67,"fee":[[0.1,"DOT",1.2,"DOT"]]},{"market":"BINANCE","url":"https://www.binance.com/uk-UA/trade/DOT_USDT?theme=dark&type=spot","buyPrice":5.811,"buyQty":2986.61,"sellPrice":5.81,"sellQty":22.3,"fee":[[0.014,"DOT",0.028,"BNB Smart Chain (BEP20)"],[0.08,"DOT",1.5,"Polkadot"],[0.028,"DOT",0.056,"BNB Beacon Chain (BEP2)"]]}],["BNB/USDT",0.03,{"market":"OKX","url":"https://www.okx.com/ua/trade-spot/BNB-USDT","buyPrice":331.49,"buyQty":1.15,"sellPrice":331.41,"sellQty":0.2025,"fee":[]},{"market":"BINANCE","url":"https://www.binance.com/uk-UA/trade/BNB_USDT?theme=dark&type=spot","buyPrice":331.7,"buyQty":128.373,"sellPrice":331.6,"sellQty":247.802,"fee":[[0.0005,"BNB",0.01,"BNB Smart Chain (BEP20)"],[0.0005,"BNB",0.01,"BNB Beacon Chain (BEP2)"],[0,"BNB",0.012,"Ethereum (ERC20)"]]}],["BETH/USDT",0.03,{"market":"BINANCE","url":"https://www.binance.com/uk-UA/trade/BETH_USDT?theme=dark&type=spot","buyPrice":1812.19,"buyQty":0.7789,"sellPrice":1811.5,"sellQty":0.0615,"fee":[[0.000057,"BETH",0.00011,"BNB Smart Chain (BEP20)"]]},{"market":"OKX","url":"https://www.okx.com/ua/trade-spot/BETH-USDT","buyPrice":1814.16,"buyQty":0.27,"sellPrice":1812.73,"sellQty":0.00605,"fee":[]}],["ARB/USDT",0.03,{"market":"OKX","url":"https://www.okx.com/ua/trade-spot/ARB-USDT","buyPrice":1.3068,"buyQty":744.19,"sellPrice":1.3066,"sellQty":9.57,"fee":[]},{"market":"BINANCE","url":"https://www.binance.com/uk-UA/trade/ARB_USDT?theme=dark&type=spot","buyPrice":1.3074,"buyQty":704.9,"sellPrice":1.3072,"sellQty":1696.9,"fee":[[0.3,"ARB",2,"Arbitrum One"],[4.84,"ARB",9.68,"Ethereum (ERC20)"]]}],["SAITAMA/USDT",0.03,{"market":"OKX","url":"https://www.okx.com/ua/trade-spot/SAITAMA-USDT","buyPrice":0.0015,"buyQty":9844,"sellPrice":0.001497,"sellQty":1034,"fee":[]},{"market":"MEXC","url":"https://www.mexc.com/exchange/SAITAMA_USDT","buyPrice":0.0015136,"buyQty":46413,"sellPrice":0.0015004,"sellQty":31893,"fee":[[3000,"SAITAMA",6000,"ERC20"]]}],["XLM/USDT",0.02,{"market":"OKX","url":"https://www.okx.com/ua/trade-spot/XLM-USDT","buyPrice":0.09278,"buyQty":8300.82,"sellPrice":0.09277,"sellQty":0,"fee":[]},{"market":"BINANCE","url":"https://www.binance.com/uk-UA/trade/XLM_USDT?theme=dark&type=spot","buyPrice":0.0929,"buyQty":317384,"sellPrice":0.0928,"sellQty":80189,"fee":[[1.04,"XLM",2.08,"BNB Smart Chain (BEP20)"],[0.02,"XLM",40,"Stellar Network"]]}],["SUSHI/USDT",0.02,{"market":"MEXC","url":"https://www.mexc.com/exchange/SUSHI_USDT","buyPrice":1.0218,"buyQty":127.42,"sellPrice":1.0198,"sellQty":211,"fee":[[5.5,"SUSHI",2,"ERC20"],[0.0001,"SUSHI",0.0002,"SOL"]]},{"market":"BINANCE","url":"https://www.binance.com/uk-UA/trade/SUSHI_USDT?theme=dark&type=spot","buyPrice":1.023,"buyQty":19369.6,"sellPrice":1.022,"sellQty":272.5,"fee":[[0.071,"SUSHI",0.14,"BNB Smart Chain (BEP20)"],[0.16,"SUSHI",0.32,"BNB Beacon Chain (BEP2)"],[6.2,"SUSHI",12,"Ethereum (ERC20)"]]}],["1INCH/USDT",0.02,{"market":"OKX","url":"https://www.okx.com/ua/trade-spot/1INCH-USDT","buyPrice":0.4719,"buyQty":1645.49,"sellPrice":0.4718,"sellQty":375.01,"fee":[]},{"market":"BINANCE","url":"https://www.binance.com/uk-UA/trade/1INCH_USDT?theme=dark&type=spot","buyPrice":0.473,"buyQty":72313.7,"sellPrice":0.472,"sellQty":15188.5,"fee":[[0.16,"1INCH",0.32,"BNB Smart Chain (BEP20)"],[13,"1INCH",26,"Ethereum (ERC20)"]]}],["CFX/USDT",0.02,{"market":"OKX","url":"https://www.okx.com/ua/trade-spot/CFX-USDT","buyPrice":0.28144,"buyQty":1850,"sellPrice":0.28138,"sellQty":1175.6,"fee":[]},{"market":"BINANCE","url":"https://www.binance.com/uk-UA/trade/CFX_USDT?theme=dark&type=spot","buyPrice":0.2816,"buyQty":16928,"sellPrice":0.2815,"sellQty":7373,"fee":[[0.41,"CFX",0.82,"BNB Smart Chain (BEP20)"]]}],["DAI/USDT",0.02,{"market":"MEXC","url":"https://www.mexc.com/exchange/DAI_USDT","buyPrice":0.9997,"buyQty":485.34,"sellPrice":0.9996,"sellQty":38666.72,"fee":[[8,"DAI",20,"ERC20"]]},{"market":"OKX","url":"https://www.okx.com/ua/trade-spot/DAI-USDT","buyPrice":1,"buyQty":1074.92,"sellPrice":0.9999,"sellQty":4765.98,"fee":[]}],["CSPR/USDT",0.02,{"market":"OKX","url":"https://www.okx.com/ua/trade-spot/CSPR-USDT","buyPrice":0.04878,"buyQty":5250,"sellPrice":0.04874,"sellQty":1694.05,"fee":[]},{"market":"MEXC","url":"https://www.mexc.com/exchange/CSPR_USDT","buyPrice":0.04887,"buyQty":173440.4,"sellPrice":0.04879,"sellQty":7965.15,"fee":[[0.001,"CSPR",3,"CSPR"]]}],["LINK/USDT",0.01,{"market":"OKX","url":"https://www.okx.com/ua/trade-spot/LINK-USDT","buyPrice":7.035,"buyQty":1035.87,"sellPrice":7.034,"sellQty":0,"fee":[]},{"market":"BINANCE","url":"https://www.binance.com/uk-UA/trade/LINK_USDT?theme=dark&type=spot","buyPrice":7.037,"buyQty":327.19,"sellPrice":7.036,"sellQty":350.4,"fee":[[0.013,"LINK",0.026,"BNB Smart Chain (BEP20)"],[0.002,"LINK",0.01,"BNB Beacon Chain (BEP2)"],[0.91,"LINK",1.82,"Ethereum (ERC20)"]]}],["MATIC/USDT",0.01,{"market":"MEXC","url":"https://www.mexc.com/exchange/MATIC_USDT","buyPrice":0.9518,"buyQty":16466.1,"sellPrice":0.9517,"sellQty":5166,"fee":[[8,"MATIC",6,"ERC20"],[0.15,"MATIC",2,"MATIC"]]},{"market":"BINANCE","url":"https://www.binance.com/uk-UA/trade/MATIC_USDT?theme=dark&type=spot","buyPrice":0.952,"buyQty":6348.7,"sellPrice":0.9519,"sellQty":4714.1,"fee":[[0.074,"MATIC",0.15,"BNB Smart Chain (BEP20)"],[0.1,"MATIC",10,"Polygon"],[0.17,"MATIC",0.34,"BNB Beacon Chain (BEP2)"],[9.72,"MATIC",19.44,"Ethereum (ERC20)"]]}],["GMX/USDT",0.01,{"market":"OKX","url":"https://www.okx.com/ua/trade-spot/GMX-USDT","buyPrice":71.04,"buyQty":3.5,"sellPrice":71.01,"sellQty":3.5,"fee":[]},{"market":"BINANCE","url":"https://www.binance.com/uk-UA/trade/GMX_USDT?theme=dark&type=spot","buyPrice":71.08,"buyQty":14.878,"sellPrice":71.05,"sellQty":11.35,"fee":[[0.02,"GMX",0.1,"AVAX C-Chain"],[0.006,"GMX",0.1,"Arbitrum One"]]}],["USTC/USDT",0.01,{"market":"OKX","url":"https://www.okx.com/ua/trade-spot/USTC-USDT","buyPrice":0.01921,"buyQty":34000,"sellPrice":0.0192,"sellQty":109937.06,"fee":[]},{"market":"BINANCE","url":"https://www.binance.com/uk-UA/trade/USTC_USDT?theme=dark&type=spot","buyPrice":0.01923097,"buyQty":1302,"sellPrice":0.01921262,"sellQty":6376,"fee":[[0.6,"USTC",200,"Terra Classic"]]}]]}